odoo/addons/stock_picking_type_shipping_policy/README.rst
odoo/addons/stock_picking_type_shipping_policy/__init__.py
odoo/addons/stock_picking_type_shipping_policy/__manifest__.py
odoo/addons/stock_picking_type_shipping_policy/i18n/es_AR.po
odoo/addons/stock_picking_type_shipping_policy/i18n/es_MX.po
odoo/addons/stock_picking_type_shipping_policy/i18n/stock_picking_type_shipping_policy.pot
odoo/addons/stock_picking_type_shipping_policy/models/__init__.py
odoo/addons/stock_picking_type_shipping_policy/models/stock_move.py
odoo/addons/stock_picking_type_shipping_policy/models/stock_picking_type.py
odoo/addons/stock_picking_type_shipping_policy/readme/CONTRIBUTORS.rst
odoo/addons/stock_picking_type_shipping_policy/readme/CREDITS.rst
odoo/addons/stock_picking_type_shipping_policy/readme/DESCRIPTION.rst
odoo/addons/stock_picking_type_shipping_policy/static/description/icon.png
odoo/addons/stock_picking_type_shipping_policy/static/description/index.html
odoo/addons/stock_picking_type_shipping_policy/tests/__init__.py
odoo/addons/stock_picking_type_shipping_policy/tests/test_stock_picking_type_shipping_policy.py
odoo/addons/stock_picking_type_shipping_policy/views/stock_picking_type.xml
odoo14_addon_stock_picking_type_shipping_policy-14.0.1.1.0.dist-info/METADATA
odoo14_addon_stock_picking_type_shipping_policy-14.0.1.1.0.dist-info/WHEEL
odoo14_addon_stock_picking_type_shipping_policy-14.0.1.1.0.dist-info/top_level.txt
odoo14_addon_stock_picking_type_shipping_policy-14.0.1.1.0.dist-info/RECORD
